bigsansar/__init__.py
bigsansar/admin.py
bigsansar/apps.py
bigsansar/models.py
bigsansar/tests.py
bigsansar/urls.py
bigsansar/views.py
bigsansar/contrib/__init__.py
bigsansar/contrib/urls.py
bigsansar/contrib/views.py
bigsansar/contrib/account/__init__.py
bigsansar/contrib/account/admin.py
bigsansar/contrib/account/apps.py
bigsansar/contrib/account/forms.py
bigsansar/contrib/account/models.py
bigsansar/contrib/account/signals.py
bigsansar/contrib/account/tests.py
bigsansar/contrib/account/urls.py
bigsansar/contrib/account/views.py
bigsansar/contrib/account/migrations/0001_initial.py
bigsansar/contrib/account/migrations/0002_alter_userinfo_options.py
bigsansar/contrib/account/migrations/__init__.py
bigsansar/contrib/account/templates/__init__.py
bigsansar/contrib/advance/__init__.py
bigsansar/contrib/advance/admin.py
bigsansar/contrib/advance/apps.py
bigsansar/contrib/advance/cf_url.py
bigsansar/contrib/advance/forms.py
bigsansar/contrib/advance/models.py
bigsansar/contrib/advance/tests.py
bigsansar/contrib/advance/urls.py
bigsansar/contrib/advance/views.py
bigsansar/contrib/advance/migrations/0001_initial.py
bigsansar/contrib/advance/migrations/0002_alter_css_options.py
bigsansar/contrib/advance/migrations/0003_javascript.py
bigsansar/contrib/advance/migrations/0004_alter_javascript_options.py
bigsansar/contrib/advance/migrations/0005_delete_css.py
bigsansar/contrib/advance/migrations/0006_delete_javascript.py
bigsansar/contrib/advance/migrations/0007_initial.py
bigsansar/contrib/advance/migrations/0008_sidebarsettings.py
bigsansar/contrib/advance/migrations/0009_sidebarsettings_user.py
bigsansar/contrib/advance/migrations/0010_cloudflare_api.py
bigsansar/contrib/advance/migrations/0011_rename_account_global_api_key_cloudflare_api_global_api_key.py
bigsansar/contrib/advance/migrations/0012_cloudflare_api_ip_address_cloudflare_api_ip_address2.py
bigsansar/contrib/advance/migrations/__init__.py
bigsansar/contrib/advance/templatetags/__init__.py
Bigsansar-2.6.5.dist-info/LICENSE
Bigsansar-2.6.5.dist-info/METADATA
Bigsansar-2.6.5.dist-info/WHEEL
Bigsansar-2.6.5.dist-info/entry_points.txt
Bigsansar-2.6.5.dist-info/top_level.txt
Bigsansar-2.6.5.dist-info/RECORD
