Metadata-Version: 2.1
Name: Bigsansar
Version: 2.6.5
Summary: Build one in minutes with bigsansar - a visual site building tool!
Home-page: https://github.com/pokhrelb9/bigsansar
Author: Bikash Pokhrel
Author-email: bigsansaroffice@gmail.com
Project-URL: Bug Tracker, https://github.com/pokhrelb9/bigsansar/issues
Project-URL: Documentations, https://docs.bigsansar.com/
Keywords: python,django host,bigsansar,django,django sites framework,django flatpages
Classifier: Programming Language :: Python :: 3
Classifier: License :: OSI Approved :: MIT License
Classifier: Operating System :: POSIX :: Linux
Classifier: Operating System :: OS Independent
Requires-Python: >=3.6
License-File: LICENSE
Requires-Dist: django
Requires-Dist: django-phonenumber-field[phonenumberslite]
Requires-Dist: django-ckeditor
Requires-Dist: requests
Requires-Dist: pillow
Requires-Dist: fontawesomefree
